pyatrea/__init__.py
pyatrea-0.9.9.dist-info/LICENSE
pyatrea-0.9.9.dist-info/METADATA
pyatrea-0.9.9.dist-info/WHEEL
pyatrea-0.9.9.dist-info/top_level.txt
pyatrea-0.9.9.dist-info/RECORD
