Metadata-Version: 2.1
Name: pyatrea
Version: 0.9.9
Summary: Python library for communication with Atrea ventilation units
Home-page: https://github.com/JurajNyiri/pyatrea
Author: Juraj Nyíri
Author-email: juraj.nyiri@gmail.com
License: UNKNOWN
Platform: UNKNOWN
Classifier: Programming Language :: Python :: 3
Classifier: License :: OSI Approved :: MIT License
Classifier: Operating System :: OS Independent
License-File: LICENSE
Requires-Dist: requests
